{
  "main": {
    "id": "bd4d87e578673f3f",
    "type": "split",
    "children": [
      {
        "id": "3e698406ff5c971c",
        "type": "tabs",
        "children": [
          {
            "id": "d0c98190ee3ac4ed",
            "type": "leaf",
            "state": {
              "type": "empty",
              "state": {},
              "icon": "lucide-file",
              "title": "新标签页"
            }
          }
        ]
      }
    ],
    "direction": "vertical"
  },
  "left": {
    "id": "6c58563dab178c5d",
    "type": "split",
    "children": [
      {
        "id": "c1700466898b5010",
        "type": "tabs",
        "children": [
          {
            "id": "62297db22c4512c3",
            "type": "leaf",
            "state": {
              "type": "file-explorer",
              "state": {
                "sortOrder": "alphabetical",
                "autoReveal": false
              },
              "icon": "lucide-folder-closed",
              "title": "文件列表"
            }
          },
          {
            "id": "e62d2f2fb510a610",
            "type": "leaf",
            "state": {
              "type": "search",
              "state": {
                "query": "tag:#dedcd1",
                "matchingCase": false,
                "explainSearch": false,
                "collapseAll": false,
                "extraContext": false,
                "sortOrder": "alphabetical"
              },
              "icon": "lucide-search",
              "title": "搜索"
            }
          },
          {
            "id": "a51d5b9dd88398f3",
            "type": "leaf",
            "state": {
              "type": "bookmarks",
              "state": {},
              "icon": "lucide-bookmark",
              "title": "书签"
            }
          }
        ],
        "currentTab": 1
      }
    ],
    "direction": "horizontal",
    "width": 300
  },
  "right": {
    "id": "9344df50540fec77",
    "type": "split",
    "children": [
      {
        "id": "66691a0857dc73d1",
        "type": "tabs",
        "children": [
          {
            "id": "29c16baca291437e",
            "type": "leaf",
            "state": {
              "type": "backlink",
              "state": {
                "collapseAll": false,
                "extraContext": false,
                "sortOrder": "alphabetical",
                "showSearch": false,
                "searchQuery": "",
                "backlinkCollapsed": false,
                "unlinkedCollapsed": true
              },
              "icon": "links-coming-in",
              "title": "反向链接"
            }
          },
          {
            "id": "2ea32740daabbb89",
            "type": "leaf",
            "state": {
              "type": "outgoing-link",
              "state": {
                "linksCollapsed": false,
                "unlinkedCollapsed": true
              },
              "icon": "links-going-out",
              "title": "出链"
            }
          },
          {
            "id": "c9e34e8fa0630076",
            "type": "leaf",
            "state": {
              "type": "tag",
              "state": {
                "sortOrder": "frequency",
                "useHierarchy": true,
                "showSearch": false,
                "searchQuery": ""
              },
              "icon": "lucide-tags",
              "title": "标签"
            }
          },
          {
            "id": "715720ad582c6eb6",
            "type": "leaf",
            "state": {
              "type": "all-properties",
              "state": {
                "sortOrder": "frequency",
                "showSearch": false,
                "searchQuery": ""
              },
              "icon": "lucide-archive",
              "title": "添加笔记属性"
            }
          },
          {
            "id": "e24cc48697a1d6dd",
            "type": "leaf",
            "state": {
              "type": "outline",
              "state": {
                "followCursor": false,
                "showSearch": false,
                "searchQuery": ""
              },
              "icon": "lucide-list",
              "title": "大纲"
            }
          }
        ]
      }
    ],
    "direction": "horizontal",
    "width": 300,
    "collapsed": true
  },
  "left-ribbon": {
    "hiddenItems": {
      "switcher:打开快速切换": false,
      "graph:查看关系图谱": false,
      "canvas:新建白板": false,
      "daily-notes:打开/创建今天的日记": false,
      "templates:插入模板": false,
      "command-palette:打开命令面板": false,
      "bases:创建新数据库": false
    }
  },
  "active": "d0c98190ee3ac4ed",
  "lastOpenFiles": [
    "DESIGN.md",
    "未命名.canvas",
    "未命名.base",
    "未命名 1.base",
    "content/kafka/_index.md",
    "content/_index.md",
    "content/kafka/KRaftOrZookeeper.md",
    "content/未命名"
  ]
}